cfwatch.py
cfwatch-0.3.0.dist-info/LICENSE
cfwatch-0.3.0.dist-info/METADATA
cfwatch-0.3.0.dist-info/WHEEL
cfwatch-0.3.0.dist-info/entry_points.txt
cfwatch-0.3.0.dist-info/top_level.txt
cfwatch-0.3.0.dist-info/RECORD
