Metadata-Version: 2.1
Name: cfwatch
Version: 0.3.0
Summary: Automagically purges CloudFlare's cache when local files are updated.
Home-page: https://github.com/quantum5/cfwatch
Author: Quantum
Author-email: quantum@dmoj.ca
License: MIT
Keywords: cloudflare cdn cache purge
Platform: UNKNOWN
Classifier: Development Status :: 3 - Alpha
Classifier: Environment :: Web Environment
Classifier: Intended Audience :: System Administrators
Classifier: License :: OSI Approved :: MIT License
Classifier: Operating System :: OS Independent
Classifier: Programming Language :: Python
Classifier: Topic :: Internet :: WWW/HTTP
Classifier: Topic :: Internet :: WWW/HTTP :: Site Management
License-File: LICENSE
Requires-Dist: requests
Requires-Dist: watchdog
